mcp_document_reader/__init__.py
mcp_document_reader/readers.py
mcp_document_reader/server.py
orange1_mcp_document_reader-0.1.1.dist-info/LICENSE
orange1_mcp_document_reader-0.1.1.dist-info/METADATA
orange1_mcp_document_reader-0.1.1.dist-info/WHEEL
orange1_mcp_document_reader-0.1.1.dist-info/entry_points.txt
orange1_mcp_document_reader-0.1.1.dist-info/RECORD
