Metadata-Version: 2.3
Name: orange1-mcp-document-reader
Version: 0.1.1
Summary: A MCP Server for reading PDF and EPUB files.
Author: Jerome Boisvert-Chouinard
Author-email: me@jbchouinard.net
Requires-Python: >=3.11,<4
Classifier: Programming Language :: Python :: 3
Classifier: Programming Language :: Python :: 3.11
Classifier: Programming Language :: Python :: 3.12
Classifier: Programming Language :: Python :: 3.13
Requires-Dist: beautifulsoup4 (>=4.13.3,<5.0.0)
Requires-Dist: ebooklib (>=0.18,<0.19)
Requires-Dist: mcp[cli] (>=1.3.0,<2.0.0)
Requires-Dist: pypdf (>=5.3.1,<6.0.0)
Requires-Dist: rich (>=13.9.4,<14.0.0)
